fm_font_rename/__init__.py
fm_font_rename/fm_font_rename.py
fm_font_rename-0.2.2.dist-info/entry_points.txt
fm_font_rename-0.2.2.dist-info/LICENSE.txt
fm_font_rename-0.2.2.dist-info/METADATA
fm_font_rename-0.2.2.dist-info/WHEEL
fm_font_rename-0.2.2.dist-info/RECORD
